sgamesolver/__init__.py
sgamesolver/homcont.py
sgamesolver/sgame.py
sgamesolver/homotopy/__init__.py
sgamesolver/homotopy/_logtracing.py
sgamesolver/homotopy/_logtracing_ct.cp36-win_amd64.pyd
sgamesolver/homotopy/_qre.py
sgamesolver/homotopy/_qre_ct.cp36-win_amd64.pyd
sgamesolver/homotopy/_shared_ct.cp36-win_amd64.pyd
sgamesolver/utility/excel_timings.py
sgamesolver/utility/sgame_conversion.py
sgamesolver-1.0.post3.dist-info/LICENSE
sgamesolver-1.0.post3.dist-info/METADATA
sgamesolver-1.0.post3.dist-info/WHEEL
sgamesolver-1.0.post3.dist-info/entry_points.txt
sgamesolver-1.0.post3.dist-info/top_level.txt
sgamesolver-1.0.post3.dist-info/RECORD
