Metadata-Version: 2.1
Name: sgamesolver
Version: 1.0.post3
Summary: A homotopy-based solver for stochastic games
Home-page: https://github.com/davidpoensgen/sgamesolver
Author: Steffen Eibelshäuser, David Poensgen
Author-email: steffen.eibelshaeuser@gmail.com, davidpoensgenecon@gmail.com
License: UNKNOWN
Project-URL: github, https://github.com/davidpoensgen/sgamesolver/
Project-URL: Bug Tracker, https://github.com/davidpoensgen/sgamesolver/issues
Project-URL: Documentation, https://sgamesolver.readthedocs.io/en/latest/
Project-URL: Please cite this paper, https://dx.doi.org/10.2139/ssrn.3316631
Keywords: game theory,stochastic games,stationary equilibrium,Markov perfect equilibrium,homotopy method,computational economics
Platform: UNKNOWN
Classifier: Programming Language :: Python :: 3
Classifier: Programming Language :: Python :: 3.6
Classifier: Programming Language :: Python :: 3.7
Classifier: Programming Language :: Python :: 3.8
Classifier: Programming Language :: Python :: 3.9
Classifier: Programming Language :: Python :: 3.10
Classifier: Programming Language :: Cython
Classifier: License :: OSI Approved :: MIT License
Classifier: Operating System :: OS Independent
Classifier: Topic :: Scientific/Engineering
Classifier: Topic :: Scientific/Engineering :: Mathematics
Classifier: Intended Audience :: Science/Research
Requires-Python: >=3.6
License-File: LICENSE
Requires-Dist: numpy
Requires-Dist: scipy
Requires-Dist: cython
Requires-Dist: pandas
Requires-Dist: matplotlib
